autopage/__init__.py
autopage/argparse.py
autopage/tests/__init__.py
autopage/tests/sinks.py
autopage/tests/test_argparse.py
autopage/tests/test_autopage.py
autopage/tests/test_line_buffer_from_input.py
autopage/tests/test_pager_settings.py
autopage-0.3.1.dist-info/LICENSE
autopage-0.3.1.dist-info/METADATA
autopage-0.3.1.dist-info/WHEEL
autopage-0.3.1.dist-info/top_level.txt
autopage-0.3.1.dist-info/RECORD
