Metadata-Version: 2.1
Name: autopage
Version: 0.3.1
Summary: A library to provide automatic paging for console output
Home-page: https://github.com/zaneb/autopage
Author: Zane Bitter
Author-email: zbitter@redhat.com
License: UNKNOWN
Platform: UNKNOWN
Classifier: License :: OSI Approved
Classifier: License :: OSI Approved :: Apache Software License
Classifier: Programming Language :: Python :: 3
Classifier: Programming Language :: Python :: 3 :: Only
Classifier: Programming Language :: Python :: 3.6
Classifier: Programming Language :: Python :: 3.7
Classifier: Programming Language :: Python :: 3.8
Classifier: Programming Language :: Python :: 3.9
Classifier: Operating System :: POSIX
Classifier: Environment :: Console
Classifier: Intended Audience :: Developers
Classifier: Topic :: Software Development :: Libraries
Classifier: Topic :: Software Development :: Libraries :: Python Modules
Classifier: Topic :: Terminals
Classifier: Topic :: Utilities
Requires-Python: >=3.6
License-File: LICENSE
